{
  "FileRecords": [
    {
      "sno": "1",
      "fileno": 101,
      "acn": "ACN-09879",
      "companyname": "United Rentals",
      "appDate": "02/06/2021",
      "transactionno": "",
      "status": "prescreening",
      "newCompany": false,
      "action":true
    },
    {
      "sno": "2",
      "fileno": 102,
      "acn": "ACN-09878",
      "companyname": "Sunbelt Rentals",
      "appDate": "02/02/2021",
      "transactionno": "",
      "status": "mailscreening",
      "newCompany": false,
      "action":true
    },

    {
      "sno": "3",
      "fileno": 103,
      "acn": "ACN-20936",
      "companyname": "RDO Vermer",
      "appDate": "01/06/2021",
      "transactionno": "",
      "status": "mailscreening",
      "newCompany": false,
      "action":true
    },
    {
      "sno": "4",
      "fileno": 104,
      "acn": "ACN-01936",
      "companyname": "MoonShine Rentals",
      "appDate": "01/16/2021",
      "transactionno": "976637",
      "status": "dataentry",
      "newCompany": false,
      "action":true
    },
    {
      "sno": "5",
      "fileno": 105,
      "acn": "ACN-01936",
      "companyname": "MoonShine Rentals",
      "appDate": "01/16/2021",
      "transactionno": "998987",
      "status": "dataentry",
      "action":true
    },
    {
      "sno": "6",
      "fileno": 106,
      "acn": "ACN-12936",
      "companyname": "Penhall Company",
      "appDate": "01/16/2021",
      "transactionno": "096637",
      "status": "paymentreview",
      "newCompany": false,
      "action":true
    },
    {
      "sno": "7",
      "fileno": 107,
      "acn": "ACN-23936",
      "companyname": "Robertson's",
      "appDate": "01/10/2021",
      "transactionno": "186637",
      "status": "closeout",
      "newCompany": false,
      "action":true
    },
    {
      "sno": "8",
      "fileno": 108,
      "acn": "ACN-12936",
      "companyname": "Delta Air Lines, Inc.",
      "appDate": "01/16/2021",
      "transactionno": "198637",
      "status": "billinginvoicing",
      "newCompany": false,
      "action":true
    },
    {
      "sno": "9",
      "fileno": 109,
      "acn": "ACN-32936",
      "companyname": "United Airlines, Inc.",
      "appDate": "01/12/2021",
      "transactionno": "186637",
      "status": "billinginvoicing",
      "newCompany": false,
      "action":true
    },
    {
      "sno": "10",
      "fileno": 110,
      "acn": null,
      "companyName": null,
      "appDate": "02/19/2020",
      "status": "mailscreening",
      "newCompany": true,
      "action":true
    },
    {
      "sno": "11",
      "fileno": 111,
      "acn": null,
      "companyName": null,
      "appDate": "02/21/2020",
      "status": "prescreening",
      "newCompany": true,
      "action":true
    }
  ]
}
